mkdocs_bpmn_js/__init__.py
mkdocs_bpmn_js/plugin.py
mkdocs_bpmn_js-0.2.0.dist-info/METADATA
mkdocs_bpmn_js-0.2.0.dist-info/WHEEL
mkdocs_bpmn_js-0.2.0.dist-info/entry_points.txt
mkdocs_bpmn_js-0.2.0.dist-info/licenses/LICENSE
mkdocs_bpmn_js-0.2.0.dist-info/RECORD
