Metadata-Version: 2.4
Name: mkdocs-bpmn-js
Version: 0.2.0
Summary: MkDocs plugin for embedding BPMN files via bpmn-js
Project-URL: Repository, https://github.com/madebyherzblut/mkdocs-bpmn-js
Author: Christian Schuhmann
License-Expression: MIT
License-File: LICENSE
Keywords: bpmn,bpmn-js,mkdocs,plugin
Classifier: Development Status :: 3 - Alpha
Classifier: Framework :: MkDocs
Classifier: Intended Audience :: Developers
Classifier: License :: OSI Approved :: MIT License
Classifier: Programming Language :: Python :: 3.8
Classifier: Programming Language :: Python :: 3.9
Classifier: Programming Language :: Python :: 3.10
Classifier: Programming Language :: Python :: 3.11
Classifier: Programming Language :: Python :: 3.12
Classifier: Topic :: Documentation
Requires-Python: >=3.8
Requires-Dist: beautifulsoup4>=4.13.4
Requires-Dist: mkdocs>=1.5.0
